aioccl/__init__.py
aioccl/device.py
aioccl/exception.py
aioccl/sensor.py
aioccl/server.py
aioccl-2025.7.dist-info/licenses/LICENSE
aioccl-2025.7.dist-info/METADATA
aioccl-2025.7.dist-info/WHEEL
aioccl-2025.7.dist-info/top_level.txt
aioccl-2025.7.dist-info/RECORD
