Metadata-Version: 2.4
Name: aioccl
Version: 2025.7
Summary: A Python library for CCL API server
Home-page: https://github.com/CCL-Electronics-Ltd/aioccl
Download-URL: https://github.com/CCL-Electronics-Ltd/aioccl
Author: fkiscd
Author-email: fkiscd@gmail.com
License: Apache License, Version 2.0
Classifier: Development Status :: 3 - Alpha
Classifier: Intended Audience :: Developers
Classifier: Natural Language :: English
Classifier: License :: OSI Approved :: Apache Software License
Classifier: Topic :: Home Automation
Classifier: Programming Language :: Python :: 3
Classifier: Programming Language :: Python :: 3.12
License-File: LICENSE
Requires-Dist: aiohttp>3
Dynamic: author
Dynamic: author-email
Dynamic: classifier
Dynamic: description
Dynamic: description-content-type
Dynamic: download-url
Dynamic: home-page
Dynamic: license
Dynamic: license-file
Dynamic: requires-dist
Dynamic: summary
